ejercicios_ampliacion_christian_salguero/__init__.py
ejercicios_ampliacion_christian_salguero/ejercicios_ampliacion_seleccion_repeticion.py
ejercicios_ampliacion_christian_salguero-1.2.dist-info/METADATA
ejercicios_ampliacion_christian_salguero-1.2.dist-info/WHEEL
ejercicios_ampliacion_christian_salguero-1.2.dist-info/top_level.txt
ejercicios_ampliacion_christian_salguero-1.2.dist-info/RECORD
