Metadata-Version: 2.4
Name: ejercicios_ampliacion_christian_salguero
Version: 1.2
Summary: Ejercicios ampliación selección y repetición de Christian Salguero
Author: Christian Salguero
Requires-Python: >=3.8
